far_search/__init__.py
far_search/exceptions.py
far_search/tool.py
far_search_tool-0.1.9.dist-info/METADATA
far_search_tool-0.1.9.dist-info/WHEEL
far_search_tool-0.1.9.dist-info/licenses/LICENSE
far_search_tool-0.1.9.dist-info/RECORD
