Metadata-Version: 2.4
Name: far-search-tool
Version: 0.1.9
Summary: LangChain tool for semantic search over Federal Acquisition Regulations (FAR)
Project-URL: Homepage, https://github.com/blueskylineassets/far-search-tool
Project-URL: Documentation, https://github.com/blueskylineassets/far-search-tool#readme
Project-URL: Repository, https://github.com/blueskylineassets/far-search-tool
Project-URL: Bug Tracker, https://github.com/blueskylineassets/far-search-tool/issues
Project-URL: API Documentation, https://rapidapi.com/yschang/api/far-rag-federal-acquisition-regulation-search
Author-email: Daniel Chang <yschang@blueskylineassets.com>
License: MIT
License-File: LICENSE
Keywords: ai-tools,far,federal-acquisition-regulations,government-contracting,langchain,llm,rag,semantic-search
Classifier: Development Status :: 4 - Beta
Classifier: Intended Audience :: Developers
Classifier: License :: OSI Approved :: MIT License
Classifier: Operating System :: OS Independent
Classifier: Programming Language :: Python :: 3
Classifier: Programming Language :: Python :: 3.9
Classifier: Programming Language :: Python :: 3.10
Classifier: Programming Language :: Python :: 3.11
Classifier: Programming Language :: Python :: 3.12
Classifier: Topic :: Scientific/Engineering :: Artificial Intelligence
Classifier: Topic :: Software Development :: Libraries :: Python Modules
Requires-Python: >=3.9
Requires-Dist: langchain<0.4.0,>=0.1.0
Requires-Dist: pydantic>=2.0.0
Requires-Dist: requests>=2.28.0
Provides-Extra: dev
Requires-Dist: black>=23.0.0; extra == 'dev'
Requires-Dist: mypy>=1.0.0; extra == 'dev'
Requires-Dist: pytest-asyncio>=0.21.0; extra == 'dev'
Requires-Dist: pytest>=7.0.0; extra == 'dev'
Requires-Dist: ruff>=0.1.0; extra == 'dev'
